pymarble/__init__.py
pymarble/cli.py
pymarble/file.py
pymarble/fileAutomaticIdentify.py
pymarble/fileClass.py
pymarble/fileCommandLine.py
pymarble/fileInputOutput.py
pymarble/fileUtil.py
pymarble/section.py
pymarble/Resources/Icons/favicon64.png
pymarble/gui/communicate.py
pymarble/gui/configurationEditor.py
pymarble/gui/defaults.py
pymarble/gui/form.py
pymarble/gui/gui.py
pymarble/gui/metaEditor.py
pymarble/gui/misc.py
pymarble/gui/periodicity.py
pymarble/gui/rowTool.py
pymarble/gui/searchTool.py
pymarble/gui/split.py
pymarble/gui/style.py
pymarble/gui/table.py
pymarble/gui/tableHeader.py
pymarble/gui/terminologyLookup.py
pymarble-2.2.1.dist-info/LICENSE
pymarble-2.2.1.dist-info/METADATA
pymarble-2.2.1.dist-info/WHEEL
pymarble-2.2.1.dist-info/entry_points.txt
pymarble-2.2.1.dist-info/top_level.txt
pymarble-2.2.1.dist-info/RECORD
