Metadata-Version: 2.1
Name: pymarble
Version: 2.2.1
Summary: "Scientific instruments produce proprietary binary data that contains a multitude of primary and metadata. This project aims to create a software that supports the domain scientist in deciphering this data and metadata and supply python scripts that decipher the instrument measurements."
Home-page: https://micromechanics.github.io/marble/
Author: Steffen Brinckmann, FionaDMello and the pyMARBLE team
Author-email: sbrinckm@gmail.com
License: MIT
Platform: UNKNOWN
Classifier: Programming Language :: Python
Classifier: License :: OSI Approved :: BSD License
Classifier: Programming Language :: Python :: 3
Requires-Python: >=3.7
License-File: LICENSE
Requires-Dist: QtAwesome
Requires-Dist: aiohttp
Requires-Dist: h5py
Requires-Dist: matplotlib
Requires-Dist: pandas
Requires-Dist: prettytable
Requires-Dist: pyside6
Requires-Dist: sortedcontainers
Provides-Extra: devel
Requires-Dist: coverage ; extra == 'devel'
Requires-Dist: pytest ; extra == 'devel'
Requires-Dist: pytest-cov ; extra == 'devel'
Requires-Dist: pytest-qt ; extra == 'devel'
Requires-Dist: pytest-xvfb ; extra == 'devel'
Requires-Dist: sphinx ; extra == 'devel'
Requires-Dist: sphinx-rtd-theme ; extra == 'devel'
